libsecp256k1_0/__init__.py
libsecp256k1_0/__main__.py
libsecp256k1_0/libsecp256k1.py
libsecp256k1_0/local_compiler.sh
libsecp256k1_0/main.py
libsecp256k1_0/compiled/darwin/libsecp256k1.0.dylib
libsecp256k1_0/compiled/unix/libsecp256k1.so.0
libsecp256k1_0/compiled/win32bit/libsecp256k1-0.dll
libsecp256k1_0/compiled/win64bit/libsecp256k1-0.dll
libsecp256k1_0/docker/Dockerfile
libsecp256k1_0/docker/compiler.sh
libsecp256k1_0/docker/helper.sh
libsecp256k1_0/docker/make_libsecp256k1.sh
libsecp256k1_0/docker/require.sh
libsecp256k1_0/utils/__init__.py
libsecp256k1_0/utils/crawler.py
libsecp256k1_0/utils/docker.py
libsecp256k1_0-0.3.0.dist-info/LICENSE
libsecp256k1_0-0.3.0.dist-info/METADATA
libsecp256k1_0-0.3.0.dist-info/WHEEL
libsecp256k1_0-0.3.0.dist-info/entry_points.txt
libsecp256k1_0-0.3.0.dist-info/top_level.txt
libsecp256k1_0-0.3.0.dist-info/RECORD
