Metadata-Version: 2.1
Name: libsecp256k1-0
Version: 0.3.0
Summary: Compiled libsecp256k1 for using ECDSA signatures and secret/public key cryptography in your python projects.
Home-page: https://github.com/ArcticTechnology/libsecp256k1-0
Author: ArcticTechnology
Author-email: arctic.technology.mail@gmail.com
License: MIT
Keywords: bitcoin,cryptography,ecdsa
Classifier: Development Status :: 5 - Production/Stable
Classifier: License :: OSI Approved :: MIT License
Classifier: Natural Language :: English
Classifier: Operating System :: OS Independent
Classifier: Programming Language :: Python
Classifier: Programming Language :: Python :: 3
Classifier: Programming Language :: Python :: 3 :: Only
Classifier: Programming Language :: Python :: 3.8
Classifier: Programming Language :: Python :: 3.9
Classifier: Programming Language :: Python :: 3.10
Classifier: Programming Language :: Python :: 3.11
Classifier: Intended Audience :: Developers
Classifier: Intended Audience :: Science/Research
Classifier: Intended Audience :: Information Technology
Classifier: Intended Audience :: Financial and Insurance Industry
Classifier: Topic :: Security
Classifier: Topic :: Security :: Cryptography
Requires-Python: >=3.8
License-File: LICENSE
